abuse/__init__.py
abuse/abuse.py
abuse-0.1.dist-info/METADATA
abuse-0.1.dist-info/RECORD
abuse-0.1.dist-info/WHEEL
abuse-0.1.dist-info/top_level.txt
